src/core_main.sv
/* 
 * Reference: https://github.com/jbush001/MiteCPU/blob/master/tinyproc.v
 ******************************************** 
 ********* Harvard Architecture CPU *********
 ********************************************
 * 
 Instruction Format:
 * bits: 
 *  11   10    9    8   7   6   5   4   3   2   1
 * [op2  op1  op0] [ O   P   E   R   A   N   D   ]
 * 
 Instruction Set:
 * 000: Add [ acc = acc + memory_op ]
 * 001: Sub [ acc = acc - memory_op ]
 * 110: And [ acc = acc & memory_op ]
 * 010: Load Immediate value [ acc = <val> ]
 * 011: Output accumulator to module's port and Store on RAM as well [ mem[data_addr] = acc AND result = acc ]
 * 100: Conditional Jump [ if acc < 0: ip_next = acc ]
 * 101:	Move memory_op to memory index, which is used to address RAM [ <no operands> ]
 * 111: No Op
 */

/* Definitions and Constants: */
`define PROGRAM_WIDTH 11
`define DATARAM_WIDTH 8
`define RAM_DEPTH 256

`define OPCFIELD 10:8 /* Opcode field */
`define OPEFIELD 7:0 /* Operand field */

/* Typedefs: */
typedef reg[`PROGRAM_WIDTH - 1:0] prog_t;
typedef reg[`DATARAM_WIDTH - 1:0] data_t;

/* Instruction Set: */
typedef enum {
	OP_ADD  /* 000 */ , OP_SUB  /* 001 */, OP_LDI  /* 010 */, OP_ST  /* 011 */, 
	OP_JMP, /* 100 */ OP_INDEX, /* 101 */  OP_AND, /* 110 */ OP_NOOP /* 111 */
} INS_SET;

module core_main (input clk, output reg[`DATARAM_WIDTH - 1:0] result);
	/* Initialize Program Memory using this task: */
	task progmem_initialize; begin
		instr(OP_LDI, 10); /* Load immediate value to acc */
		instr(OP_ST, 0); /* Store that value into data ram[0] */
		instr(OP_ADD, 0); /* Add accumulator with ram[0] */
		instr(OP_ADD, 5);
		instr(OP_ST, 0);
		instr(OP_JMP, 5);
		
		/* And so on ... */
	end endtask
	
	/* This function fills up the Program Memory one instruction at a time: */
	data_t instr_counter = 0;
	task instr;
		input [2:0] opcode;
		input [7:0] operator;
	begin
		program_mem[instr_counter] = {opcode, operator};
		instr_counter++;
	end
	endtask

/**************************************************/
/*********** START OF CORE DECLARATION ***********/
/**************************************************/
	
	/* Program Memory: */
	prog_t program_mem[0:`RAM_DEPTH - 1];
	/* Data Memory: */
	data_t data_mem[0:`RAM_DEPTH - 1];
	
	/* Instruction Pointer: */
	data_t ip = `DATARAM_WIDTH'hFF;
	wire[`DATARAM_WIDTH - 1:0] ip_next = 
		(ir[`OPCFIELD] == OP_JMP && accumulator[7]) ? 
			ir[`OPEFIELD] : /* Jump to <val> if accumulator has a minus sign bit */
			ip + 1; /* IP incremented by 1 */

	/* Registers: */
	prog_t ir = 0; /* Instruction Register */
	data_t accumulator = 0;
	data_t mem_index = 0; /* Memory index, used for addressing RAM */
	data_t memory_op = 0;
	wire[`DATARAM_WIDTH - 1:0] data_addr = ir[`OPEFIELD] + mem_index;
	
	/* Initial process: */
	initial begin
		integer i;
		/* Load up Program memory: */
		progmem_initialize;
		/* Initialize data memory: */
		for(i = 0; i < `RAM_DEPTH - 1; i++) data_mem[i] = 0;
	end
	
	/* For every negative clock edge: */
	always @(negedge clk) begin
		/* Non-blocking sequence: */
		if(ir[`OPCFIELD] == OP_ST) /* If instruction WAS (on posedge) OP_ST, then: */
			data_mem[data_addr] <= accumulator; /* Move accumulator to RAM by using memory_index register */
		else /* Else, for every other instruction, move data from RAM to memory_op: */
			memory_op <= data_mem[data_addr]; /* data_addr should be equal to ir[`OPEFIELD] */
	end
	
	/* For every positive clock edge: */
	always @(posedge clk) begin
		/* Non-blocking sequence: */
		ip <= ip_next; /* Increment instruction pointer */
		ir <= program_mem[ip_next]; /* Fetch instruction */
		mem_index <= (ir[`OPCFIELD] == OP_INDEX) ? memory_op : 0;
		
		case(ir[`OPCFIELD]) /* Decode Opcode using last 3 bits */
			OP_ADD: accumulator <= accumulator + memory_op; /* Add */
			OP_SUB: accumulator <= accumulator - memory_op; /* Sub */
			OP_AND: accumulator <= accumulator & memory_op; /* And */
			OP_LDI: accumulator <= ir[`OPEFIELD]; /* Load immediate */
			OP_ST: if(ir[`OPEFIELD] == 0) result <= accumulator; /* Output accumulator out of the module's port */
		endcase
	end
	
/**************************************************/
/*********** END OF CORE DECLARATION ***********/
/**************************************************/
endmodule

 /* (1 ns reference, 1 ps precision): */
`timescale 1ns / 1ps

module core_main_tb;
	reg clk = 0;
	wire[7:0] result;
	
	core_main core(clk, result);
	
	initial begin
		$dumpfile("core_main.vcd");
		$dumpvars(0, core_main_tb);
		$display("CPU Running!");
		repeat(300) #0.001 clk = ~clk;
		$display("Finished! (ret: %02x)", result);
	end
endmodule

waves/core_main.vcd
$date
	Sun Jun 12 16:20:34 2016
$end
$version
	Icarus Verilog
$end
$timescale
	1ps
$end
$scope module core_main_tb $end
$var wire 8 ! result [7:0] $end
$var reg 1 " clk $end
$scope module core $end
$var wire 1 " clk $end
$var wire 8 # ip_next [7:0] $end
$var wire 8 $ data_addr [7:0] $end
$var reg 8 % accumulator [7:0] $end
$var reg 8 & instr_counter [7:0] $end
$var reg 8 ' ip [7:0] $end
$var reg 11 ( ir [10:0] $end
$var reg 8 ) mem_index [7:0] $end
$var reg 8 * memory_op [7:0] $end
$var reg 8 + result [7:0] $end
$scope begin $unm_blk_3 $end
$var integer 32 , i [31:0] $end
$upscope $end
$scope task instr $end
$var reg 3 - opcode [2:0] $end
$var reg 8 . operator [7:0] $end
$upscope $end
$scope task progmem_initialize $end
$upscope $end
$upscope $end
$upscope $end
$enddefinitions $end
#0
$dumpvars
b101 .
b100 -
b11111111 ,
bx +
b0 *
b0 )
b0 (
b11111111 '
b110 &
b0 %
b0 $
b0 #
0"
bx !
$end
#1
b1010 $
b1 #
b1000001010 (
b0 '
1"
#2
0"
#3
b0 $
b10 #
b1010 %
b1100000000 (
b1 '
1"
#4
0"
#5
b11 #
b1010 !
b1010 +
b0 (
b10 '
1"
#6
b1010 *
0"
#7
b101 $
b100 #
b10100 %
b101 (
b11 '
1"
#8
b0 *
0"
#9
b0 $
b101 #
b1100000000 (
b100 '
1"
#10
0"
#11
b101 $
b110 #
b10100 !
b10100 +
b10000000101 (
b101 '
1"
#12
0"
#13
bx $
b111 #
bx (
b110 '
1"
#14
bx *
0"
#15
b1000 #
bx )
b111 '
1"
#16
0"
#17
b1001 #
b1000 '
1"
#18
0"
#19
b1010 #
b1001 '
1"
#20
0"
#21
b1011 #
b1010 '
1"
#22
0"
#23
b1100 #
b1011 '
1"
#24
0"
#25
b1101 #
b1100 '
1"
#26
0"
#27
b1110 #
b1101 '
1"
#28
0"
#29
b1111 #
b1110 '
1"
#30
0"
#31
b10000 #
b1111 '
1"
#32
0"
#33
b10001 #
b10000 '
1"
#34
0"
#35
b10010 #
b10001 '
1"
#36
0"
#37
b10011 #
b10010 '
1"
#38
0"
#39
b10100 #
b10011 '
1"
#40
0"
#41
b10101 #
b10100 '
1"
#42
0"
#43
b10110 #
b10101 '
1"
#44
0"
#45
b10111 #
b10110 '
1"
#46
0"
#47
b11000 #
b10111 '
1"
#48
0"
#49
b11001 #
b11000 '
1"
#50
0"
#51
b11010 #
b11001 '
1"
#52
0"
#53
b11011 #
b11010 '
1"
#54
0"
#55
b11100 #
b11011 '
1"
#56
0"
#57
b11101 #
b11100 '
1"
#58
0"
#59
b11110 #
b11101 '
1"
#60
0"
#61
b11111 #
b11110 '
1"
#62
0"
#63
b100000 #
b11111 '
1"
#64
0"
#65
b100001 #
b100000 '
1"
#66
0"
#67
b100010 #
b100001 '
1"
#68
0"
#69
b100011 #
b100010 '
1"
#70
0"
#71
b100100 #
b100011 '
1"
#72
0"
#73
b100101 #
b100100 '
1"
#74
0"
#75
b100110 #
b100101 '
1"
#76
0"
#77
b100111 #
b100110 '
1"
#78
0"
#79
b101000 #
b100111 '
1"
#80
0"
#81
b101001 #
b101000 '
1"
#82
0"
#83
b101010 #
b101001 '
1"
#84
0"
#85
b101011 #
b101010 '
1"
#86
0"
#87
b101100 #
b101011 '
1"
#88
0"
#89
b101101 #
b101100 '
1"
#90
0"
#91
b101110 #
b101101 '
1"
#92
0"
#93
b101111 #
b101110 '
1"
#94
0"
#95
b110000 #
b101111 '
1"
#96
0"
#97
b110001 #
b110000 '
1"
#98
0"
#99
b110010 #
b110001 '
1"
#100
0"
#101
b110011 #
b110010 '
1"
#102
0"
#103
b110100 #
b110011 '
1"
#104
0"
#105
b110101 #
b110100 '
1"
#106
0"
#107
b110110 #
b110101 '
1"
#108
0"
#109
b110111 #
b110110 '
1"
#110
0"
#111
b111000 #
b110111 '
1"
#112
0"
#113
b111001 #
b111000 '
1"
#114
0"
#115
b111010 #
b111001 '
1"
#116
0"
#117
b111011 #
b111010 '
1"
#118
0"
#119
b111100 #
b111011 '
1"
#120
0"
#121
b111101 #
b111100 '
1"
#122
0"
#123
b111110 #
b111101 '
1"
#124
0"
#125
b111111 #
b111110 '
1"
#126
0"
#127
b1000000 #
b111111 '
1"
#128
0"
#129
b1000001 #
b1000000 '
1"
#130
0"
#131
b1000010 #
b1000001 '
1"
#132
0"
#133
b1000011 #
b1000010 '
1"
#134
0"
#135
b1000100 #
b1000011 '
1"
#136
0"
#137
b1000101 #
b1000100 '
1"
#138
0"
#139
b1000110 #
b1000101 '
1"
#140
0"
#141
b1000111 #
b1000110 '
1"
#142
0"
#143
b1001000 #
b1000111 '
1"
#144
0"
#145
b1001001 #
b1001000 '
1"
#146
0"
#147
b1001010 #
b1001001 '
1"
#148
0"
#149
b1001011 #
b1001010 '
1"
#150
0"
#151
b1001100 #
b1001011 '
1"
#152
0"
#153
b1001101 #
b1001100 '
1"
#154
0"
#155
b1001110 #
b1001101 '
1"
#156
0"
#157
b1001111 #
b1001110 '
1"
#158
0"
#159
b1010000 #
b1001111 '
1"
#160
0"
#161
b1010001 #
b1010000 '
1"
#162
0"
#163
b1010010 #
b1010001 '
1"
#164
0"
#165
b1010011 #
b1010010 '
1"
#166
0"
#167
b1010100 #
b1010011 '
1"
#168
0"
#169
b1010101 #
b1010100 '
1"
#170
0"
#171
b1010110 #
b1010101 '
1"
#172
0"
#173
b1010111 #
b1010110 '
1"
#174
0"
#175
b1011000 #
b1010111 '
1"
#176
0"
#177
b1011001 #
b1011000 '
1"
#178
0"
#179
b1011010 #
b1011001 '
1"
#180
0"
#181
b1011011 #
b1011010 '
1"
#182
0"
#183
b1011100 #
b1011011 '
1"
#184
0"
#185
b1011101 #
b1011100 '
1"
#186
0"
#187
b1011110 #
b1011101 '
1"
#188
0"
#189
b1011111 #
b1011110 '
1"
#190
0"
#191
b1100000 #
b1011111 '
1"
#192
0"
#193
b1100001 #
b1100000 '
1"
#194
0"
#195
b1100010 #
b1100001 '
1"
#196
0"
#197
b1100011 #
b1100010 '
1"
#198
0"
#199
b1100100 #
b1100011 '
1"
#200
0"
#201
b1100101 #
b1100100 '
1"
#202
0"
#203
b1100110 #
b1100101 '
1"
#204
0"
#205
b1100111 #
b1100110 '
1"
#206
0"
#207
b1101000 #
b1100111 '
1"
#208
0"
#209
b1101001 #
b1101000 '
1"
#210
0"
#211
b1101010 #
b1101001 '
1"
#212
0"
#213
b1101011 #
b1101010 '
1"
#214
0"
#215
b1101100 #
b1101011 '
1"
#216
0"
#217
b1101101 #
b1101100 '
1"
#218
0"
#219
b1101110 #
b1101101 '
1"
#220
0"
#221
b1101111 #
b1101110 '
1"
#222
0"
#223
b1110000 #
b1101111 '
1"
#224
0"
#225
b1110001 #
b1110000 '
1"
#226
0"
#227
b1110010 #
b1110001 '
1"
#228
0"
#229
b1110011 #
b1110010 '
1"
#230
0"
#231
b1110100 #
b1110011 '
1"
#232
0"
#233
b1110101 #
b1110100 '
1"
#234
0"
#235
b1110110 #
b1110101 '
1"
#236
0"
#237
b1110111 #
b1110110 '
1"
#238
0"
#239
b1111000 #
b1110111 '
1"
#240
0"
#241
b1111001 #
b1111000 '
1"
#242
0"
#243
b1111010 #
b1111001 '
1"
#244
0"
#245
b1111011 #
b1111010 '
1"
#246
0"
#247
b1111100 #
b1111011 '
1"
#248
0"
#249
b1111101 #
b1111100 '
1"
#250
0"
#251
b1111110 #
b1111101 '
1"
#252
0"
#253
b1111111 #
b1111110 '
1"
#254
0"
#255
b10000000 #
b1111111 '
1"
#256
0"
#257
b10000001 #
b10000000 '
1"
#258
0"
#259
b10000010 #
b10000001 '
1"
#260
0"
#261
b10000011 #
b10000010 '
1"
#262
0"
#263
b10000100 #
b10000011 '
1"
#264
0"
#265
b10000101 #
b10000100 '
1"
#266
0"
#267
b10000110 #
b10000101 '
1"
#268
0"
#269
b10000111 #
b10000110 '
1"
#270
0"
#271
b10001000 #
b10000111 '
1"
#272
0"
#273
b10001001 #
b10001000 '
1"
#274
0"
#275
b10001010 #
b10001001 '
1"
#276
0"
#277
b10001011 #
b10001010 '
1"
#278
0"
#279
b10001100 #
b10001011 '
1"
#280
0"
#281
b10001101 #
b10001100 '
1"
#282
0"
#283
b10001110 #
b10001101 '
1"
#284
0"
#285
b10001111 #
b10001110 '
1"
#286
0"
#287
b10010000 #
b10001111 '
1"
#288
0"
#289
b10010001 #
b10010000 '
1"
#290
0"
#291
b10010010 #
b10010001 '
1"
#292
0"
#293
b10010011 #
b10010010 '
1"
#294
0"
#295
b10010100 #
b10010011 '
1"
#296
0"
#297
b10010101 #
b10010100 '
1"
#298
0"
#299
b10010110 #
b10010101 '
1"
